Metadata-Version: 2.1
Name: nonebot-plugin-eventexpiry
Version: 0.1.2
Summary: NoneBot2 event expiry filter
License: MIT
Author-email: Akirami <Akiramiaya@outlook.com>
Requires-Python: >=3.8
Requires-Dist: nonebot-adapter-onebot>=2.4.6
Requires-Dist: nonebot2>=2.4.1
Project-URL: Homepage, https://github.com/A-kirami/nonebot-plugin-eventexpiry
Project-URL: Repository, https://github.com/A-kirami/nonebot-plugin-eventexpiry
